AUTHORS.rst
CONTRIBUTING.rst
HISTORY.rst
LICENSE
MANIFEST.in
README.rst
setup.cfg
setup.py
docs/Makefile
docs/authors.rst
docs/conf.py
docs/contributing.rst
docs/history.rst
docs/index.rst
docs/installation.rst
docs/make.bat
docs/readme.rst
docs/usage.rst
t2stimulate/__init__.py
t2stimulate/t2stimulate.py
t2stimulate.egg-info/PKG-INFO
t2stimulate.egg-info/SOURCES.txt
t2stimulate.egg-info/dependency_links.txt
t2stimulate.egg-info/entry_points.txt
t2stimulate.egg-info/not-zip-safe
t2stimulate.egg-info/requires.txt
t2stimulate.egg-info/top_level.txt
tests/test_fit.py
tests/test_t2stimulate.py