Metadata-Version: 1.1
Name: t2stimulate
Version: 0.1.0
Summary: MRI T2 decay curve simulation with imperfect excitation pulse (B1)
Home-page: https://github.com/brechmos/t2stimulate
Author: Craig Jones
Author-email: craig@brechmos.org
License: GNU General Public License v3
Keywords: t2stimulate
Platform: UNKNOWN
Classifier: Development Status :: 2 - Pre-Alpha
Classifier: Intended Audience :: Developers
Classifier: License :: OSI Approved :: GNU General Public License v3 (GPLv3)
Classifier: Natural Language :: English
Classifier: Programming Language :: Python :: 3
Classifier: Programming Language :: Python :: 3.4
Classifier: Programming Language :: Python :: 3.5
Classifier: Programming Language :: Python :: 3.6
Classifier: Programming Language :: Python :: 3.7
